jupyterhub_announcement/__init__.py
jupyterhub_announcement/__main__.py
jupyterhub_announcement/announcement.py
jupyterhub_announcement/encoder.py
jupyterhub_announcement/handlers.py
jupyterhub_announcement/queue.py
jupyterhub_announcement/ssl.py
jupyterhub_announcement-0.9.2.data/data/share/jupyterhub/announcement/templates/index.html
jupyterhub_announcement-0.9.2.dist-info/LICENSE
jupyterhub_announcement-0.9.2.dist-info/METADATA
jupyterhub_announcement-0.9.2.dist-info/WHEEL
jupyterhub_announcement-0.9.2.dist-info/top_level.txt
jupyterhub_announcement-0.9.2.dist-info/RECORD
