Metadata-Version: 2.1
Name: jupyterhub-announcement
Version: 0.9.2
Summary: JupyterHub Announcement Service
Home-page: https://github.com/rcthomas/jupyterhub-announcement
Author: R. C. Thomas, François Tessier, Narek Amirbekian
Author-email: rcthomas@lbl.gov
License-File: LICENSE
Requires-Dist: aiofiles
Requires-Dist: html-sanitizer
Requires-Dist: jupyterhub
